Metadata-Version: 1.1
Name: udmurttagger
Version: 0.5.3
Summary: Utility for part-of-speech tagging of Udmurt text
Home-page: https://github.com/nevmenandr/udmurttagger
Author: Boris Orekhov
Author-email: nevmenandr@gmail.com
License: GPL
Keywords: nlp udmurt pos tagger
Platform: UNKNOWN
Classifier: Development Status :: 4 - Beta
Classifier: Natural Language :: Russian
Classifier: Programming Language :: Python :: 3.5
Classifier: Programming Language :: Python :: 3.6
Classifier: Topic :: Text Processing :: Linguistic
Classifier: Intended Audience :: Developers
